nebelung/__init__.py
nebelung/terra_workflow.py
nebelung/terra_workspace.py
nebelung/types.py
nebelung/utils.py
nebelung/wdl.py
nebelung-2.13.1.dist-info/METADATA
nebelung-2.13.1.dist-info/WHEEL
nebelung-2.13.1.dist-info/RECORD
