Metadata-Version: 2.1
Name: nebelung
Version: 2.13.1
Summary: Firecloud API Wrapper
Home-page: https://github.com/broadinstitute/nebelung
Keywords: terra,firecloud
Author: Devin McCabe
Author-email: dmccabe@broadinstitute.org
Requires-Python: >=3.11
Classifier: Programming Language :: Python :: 3
Classifier: Programming Language :: Python :: 3.11
Classifier: Programming Language :: Python :: 3.12
Classifier: Programming Language :: Python :: 3.13
Requires-Dist: firecloud-api-cds (>=0.2.0,<0.3.0)
Requires-Dist: pandas (>=1.5)
Requires-Dist: pandera[strategies] (>=0.20)
Requires-Dist: pd-flatten (>=0.1)
Requires-Dist: pydantic (>=2.8)
Requires-Dist: pygithub (>=2.3)
Project-URL: Repository, https://github.com/broadinstitute/nebelung
